{
	"configurations" : 
	[
		{
			"directories" : 
			[
				{
					"build" : ".",
					"hasInstallRule" : true,
					"jsonFile" : "directory-.-Debug-30fcdab197847d8a2593.json",
					"minimumCMakeVersion" : 
					{
						"string" : "3.0.0"
					},
					"projectIndex" : 0,
					"source" : ".",
					"targetIndexes" : 
					[
						0
					]
				}
			],
			"name" : "Debug",
			"projects" : 
			[
				{
					"directoryIndexes" : 
					[
						0
					],
					"name" : "sdl2_demo",
					"targetIndexes" : 
					[
						0
					]
				}
			],
			"targets" : 
			[
				{
					"directoryIndex" : 0,
					"id" : "sdl2_demo::@6890427a1f51a3e7e1df",
					"jsonFile" : "target-sdl2_demo-Debug-d166a2a84f7f3609770a.json",
					"name" : "sdl2_demo",
					"projectIndex" : 0
				}
			]
		}
	],
	"kind" : "codemodel",
	"paths" : 
	{
		"build" : "/Users/kevin/repos/learnOpenGL/build",
		"source" : "/Users/kevin/repos/learnOpenGL"
	},
	"version" : 
	{
		"major" : 2,
		"minor" : 3
	}
}
